LICENSE
README.rst
frozndict/__init__.py
frozndict/frozendict.py
frozndict/utils.py
frozndict-1.0.11.dist-info/LICENSE
frozndict-1.0.11.dist-info/WHEEL
frozndict-1.0.11.dist-info/METADATA
frozndict-1.0.11.dist-info/RECORD
