Metadata-Version: 2.1
Name: frozndict
Version: 1.0.11
Summary: frozndict is a memory efficient immutable dictionary.
Home-page: https://github.com/Harmouch101/frozndict
License: GNU General Public License v3.0
Keywords: python,frozendict,frozndict
Author: Mahmoud Harmouch
Author-email: eng.mahmoudharmouch@gmail.com
Requires-Python: >=3.9,<4.0
Classifier: Development Status :: 2 - Pre-Alpha
Classifier: Intended Audience :: Developers
Classifier: License :: Other/Proprietary License
Classifier: Natural Language :: English
Classifier: Programming Language :: Python :: 3
Classifier: Programming Language :: Python :: 3.10
Classifier: Programming Language :: Python :: 3.9
Project-URL: Repository, https://github.com/Harmouch101/frozndict
